archetype_core_nlp-0.1.6-py3.8-nspkg.pth
infra/core/forge/__init__.py
infra/core/forge/backend.py
infra/core/forge/base.py
infra/core/forge/consts.py
infra/core/forge/generators.py
infra/core/forge/archetype/__init__.py
infra/core/forge/archetype/configs.py
infra/core/forge/processors/processors.py
infra/core/forge/processors/analysis/__init__.py
infra/core/forge/processors/analysis/correlation.py
infra/core/forge/processors/analysis/utils.py
infra/core/forge/processors/analysis/visualization.py
infra/core/forge/processors/core/datasets.py
infra/core/forge/processors/core/functions.py
infra/core/forge/processors/core/processors.py
infra/core/forge/processors/core/utils.py
infra/core/forge/processors/core/transformers/__init__.py
infra/core/forge/processors/core/transformers/_anonimizer.py
infra/core/forge/processors/core/transformers/_lemmatizer.py
infra/core/forge/processors/core/transformers/_n_gram_filter.py
infra/core/forge/processors/core/transformers/_stemmer.py
infra/core/forge/processors/io/__init__.py
infra/core/forge/processors/io/base.py
infra/core/forge/processors/io/storage/__init__.py
infra/core/forge/processors/io/storage/adapters/__init__.py
infra/core/forge/processors/io/storage/adapters/file_system.py
infra/core/forge/processors/io/storage/adapters/google_cloud.py
infra/core/forge/processors/io/storage/adapters/storage_adapter.py
infra/core/forge/processors/io/stream/__init__.py
infra/core/forge/processors/io/stream/conforming.py
infra/core/forge/processors/io/stream/adapters/__init__.py
infra/core/forge/processors/io/stream/adapters/file.py
infra/core/forge/processors/io/stream/adapters/memory.py
infra/core/forge/processors/io/stream/adapters/stream_adapter.py
infra/core/forge/processors/models/__init__.py
infra/core/forge/processors/models/base.py
infra/core/forge/processors/models/errors.py
infra/core/forge/processors/models/functions.py
infra/core/forge/processors/models/utils.py
infra/core/forge/processors/models/drivers/__init__.py
archetype_core_nlp-0.1.6.dist-info/LICENSE
archetype_core_nlp-0.1.6.dist-info/METADATA
archetype_core_nlp-0.1.6.dist-info/WHEEL
archetype_core_nlp-0.1.6.dist-info/entry_points.txt
archetype_core_nlp-0.1.6.dist-info/namespace_packages.txt
archetype_core_nlp-0.1.6.dist-info/top_level.txt
archetype_core_nlp-0.1.6.dist-info/RECORD
