Metadata-Version: 2.1
Name: archetype-core-nlp
Version: 0.1.6
Home-page: https://github.com/EneasJr-Rodrigues/archetype-core-nlp
Author: Eneas-Rodrigues
Author-email: eneas.rodrigues25@gmail.com
Requires-Python: >=3.8
License-File: LICENSE
Requires-Dist: setuptools
Requires-Dist: wheel
Requires-Dist: PyYAML
Requires-Dist: pyspark
Requires-Dist: findspark
Requires-Dist: numpy
Requires-Dist: scipy
Requires-Dist: pandas
Requires-Dist: joblib >=0.14.1
Requires-Dist: scikit-learn >=0.23
Requires-Dist: joblibspark >=0.2.0
Requires-Dist: notedown >=1.5.1
Requires-Dist: jupyterthemes >=0.20.0
Requires-Dist: seaborn
